.gitignore
LICENSE-2.0.txt
README.rst
ez_setup.py
requirements.txt
setup.py
alloyclient/__init__.py
alloyclient/cdmi.py
alloyclient/exceptions.py
alloyclient/ui.py
alloyclient.egg-info/PKG-INFO
alloyclient.egg-info/SOURCES.txt
alloyclient.egg-info/dependency_links.txt
alloyclient.egg-info/entry_points.txt
alloyclient.egg-info/requires.txt
alloyclient.egg-info/top_level.txt