Metadata-Version: 1.1
Name: alloyclient
Version: 1.0.0
Summary: Alloy Client
Home-page: https://bitbucket.org/archiveanalytics/alloy-client
Author: John Harrison
Author-email: john.harrison@archiveanalytics.com
License: Apache License, Version 2.0
Platform: UNKNOWN
Classifier: Development Status :: 4 - Beta
Classifier: License :: OSI Approved :: Apache Software License
Classifier: Programming Language :: Python :: 2.7
Classifier: Topic :: Internet :: WWW/HTTP :: WSGI
Classifier: Topic :: Internet :: WWW/HTTP :: WSGI :: Application
Classifier: Topic :: Internet :: WWW/HTTP :: WSGI :: Middleware
Classifier: Topic :: System :: Archiving
